Metadata-Version: 1.1
Name: aioworkers-tg
Version: 0.0.1
Summary: aioworkers plugin for Telegram
Home-page: https://github.com/aioworkers/aioworkers-tg
Author: Alexander Bogushov
Author-email: abogushov@gmail.com
License: Apache Software License 2.0
Keywords: aioworkers aiotg telegram
Platform: UNKNOWN
Classifier: Development Status :: 2 - Pre-Alpha
Classifier: Intended Audience :: Developers
Classifier: License :: OSI Approved :: Apache Software License
Classifier: Programming Language :: Python :: 3
Classifier: Programming Language :: Python :: 3.6
Classifier: Programming Language :: Python :: 3.7
